robot_manager/__init__.py
robot_manager/assets.py
robot_manager/base.py
robot_manager/exceptions.py
robot_manager/flow.py
robot_manager/items.py
robot_manager/logs.py
robot_manager/nodes.py
robot_manager/queues.py
robot_manager/server.py
robot_manager/system.py
ibott_robot_manager-2.0.4.dist-info/LICENSE
ibott_robot_manager-2.0.4.dist-info/METADATA
ibott_robot_manager-2.0.4.dist-info/WHEEL
ibott_robot_manager-2.0.4.dist-info/top_level.txt
ibott_robot_manager-2.0.4.dist-info/RECORD
