Metadata-Version: 2.1
Name: ibott-robot-manager
Version: 2.0.4
Summary: This packages allows to use ibott robot console features. More information in https://ibott.io
Home-page: https://github.com/ecrespo66/robot-manager
Author: OnameDohe
Author-email: OnameDohe <enrique.crespo.debenito@gmail.com>
License: Apache License
Project-URL: Homepage, https://github.com/ecrespo66/robot-manager
Project-URL: Bug Tracker, https://github.com/ecrespo66/robot-manager/issues
Classifier: Programming Language :: Python :: 3
Classifier: License :: OSI Approved :: MIT License
Classifier: Operating System :: OS Independent
Requires-Python: >=3.7
License-File: LICENSE
Requires-Dist: hatchling
Requires-Dist: requests
Requires-Dist: python-decouple (==3.1)
